urltokenizer/__init__.py
urltokenizer/apps.py
urltokenizer/enums.py
urltokenizer/exceptions.py
urltokenizer/managers.py
urltokenizer/mixins.py
urltokenizer/models.py
urltokenizer/serializers.py
urltokenizer/token_generator.py
urltokenizer/tokenizer.py
urltokenizer/utils.py
urltokenizer/sendgrid/__init__.py
urltokenizer/sendgrid/api.py
django_url_tokenizer-0.1.56.dist-info/LICENSE
django_url_tokenizer-0.1.56.dist-info/METADATA
django_url_tokenizer-0.1.56.dist-info/WHEEL
django_url_tokenizer-0.1.56.dist-info/top_level.txt
django_url_tokenizer-0.1.56.dist-info/RECORD
