Metadata-Version: 2.1
Name: django-url-tokenizer
Version: 0.1.56
Summary: A python package that provides a Django app that allows you to generate tokenized urls and send them to users via email.
Home-page: https://github.com/nibblex/django-url-tokenizer
Author: Sergio Rodríguez
Author-email: srodriguez3441@gmail.com
Maintainer: Sergio Rodríguez
Maintainer-email: srodriguez3441@gmail.com
License: MIT
Classifier: Framework :: Django
Classifier: Framework :: Django :: 3.1
Classifier: Framework :: Django :: 3.2
Classifier: Framework :: Django :: 4.0
Classifier: Framework :: Django :: 4.1
Classifier: Framework :: Django :: 4.2
Classifier: Framework :: Django :: 5.0
Classifier: Intended Audience :: Developers
Classifier: License :: OSI Approved :: MIT License
Classifier: Operating System :: OS Independent
Classifier: Programming Language :: Python :: 3
Classifier: Programming Language :: Python :: 3.6
Classifier: Programming Language :: Python :: 3.7
Classifier: Programming Language :: Python :: 3.8
Classifier: Programming Language :: Python :: 3.9
Classifier: Programming Language :: Python :: 3.10
Classifier: Programming Language :: Python :: 3.11
Classifier: Programming Language :: Python :: 3.12
Classifier: Programming Language :: Python :: 3.13
Classifier: Topic :: Software Development :: Libraries :: Python Modules
Requires-Python: >=3.6
License-File: LICENSE
Requires-Dist: Django>=3.1
Provides-Extra: serializers
Requires-Dist: djangorestframework; extra == "serializers"
Provides-Extra: sendgrid
Requires-Dist: sendgrid; extra == "sendgrid"
Requires-Dist: jinja2; extra == "sendgrid"
Requires-Dist: relattrs; extra == "sendgrid"
Provides-Extra: sms
Requires-Dist: django-sms[twilio]; extra == "sms"
Requires-Dist: jinja2; extra == "sms"
Requires-Dist: relattrs; extra == "sms"
